setup.cfg
setup.py
dist_pkg/Binomialdistribution.py
dist_pkg/Gaussiandistribution.py
dist_pkg/Generaldistribution.py
dist_pkg/__init__.py
dist_pkg.egg-info/PKG-INFO
dist_pkg.egg-info/SOURCES.txt
dist_pkg.egg-info/dependency_links.txt
dist_pkg.egg-info/not-zip-safe
dist_pkg.egg-info/top_level.txt