Metadata-Version: 1.0
Name: dist-pkg
Version: 0.0
Summary: Distributions Test Package
Home-page: UNKNOWN
Author: UNKNOWN
Author-email: safronov@phystech.edu
License: UNKNOWN
Platform: UNKNOWN
